{
  "HBAR": {
    "0": {
      "e": 0.06853,
      "a": false,
      "p": 0.06853
    }
  },
  "OP": {
    "0": {
      "e": 0.1017,
      "a": false,
      "p": 0.1017
    }
  },
  "ADA": {
    "0": {
      "e": 0.1639,
      "a": false,
      "p": 0.1639
    }
  },
  "ALGO": {
    "0": {
      "e": 0.0838,
      "a": false,
      "p": 0.0838
    }
  },
  "APT": {
    "0": {
      "e": 0.611,
      "a": false,
      "p": 0.611
    }
  },
  "SEI": {
    "0": {
      "e": 0.04858,
      "a": false,
      "p": 0.04858
    }
  },
  "AVAX": {
    "0": {
      "e": 6.472,
      "a": false,
      "p": 6.472
    }
  }
}