{
  "ts": "2026-06-25T17:02:56.026531+03:00",
  "bull": 8,
  "bear": 23,
  "total": 31,
  "bull_pct": 26.0,
  "bull_syms": [
    "KCHOL",
    "MGROS",
    "PGSUS",
    "TAVHL",
    "THYAO",
    "TKFEN",
    "TUPRS",
    "ALARK"
  ],
  "bear_syms": [
    "AKBNK",
    "ASELS",
    "DOHOL",
    "ENKAI",
    "EREGL",
    "FROTO",
    "GUBRF",
    "HALKB",
    "ISCTR",
    "KRDMD",
    "PETKM",
    "SISE",
    "SOKM",
    "TOASO",
    "TTKOM",
    "VAKBN",
    "YKBNK",
    "AEFES",
    "HEKTS",
    "ODAS",
    "ASTOR",
    "AKSEN",
    "KONTR"
  ],
  "fresh_bear": [
    "AKBNK",
    "TOASO",
    "VAKBN"
  ]
}